py251112app/__init__.py
py251112app/__main__.py
py251112app/py.typed
py251112app/py251112app.py
py251112app-0.2.0.dist-info/WHEEL
py251112app-0.2.0.dist-info/entry_points.txt
py251112app-0.2.0.dist-info/METADATA
py251112app-0.2.0.dist-info/RECORD
