Metadata-Version: 2.3
Name: py251112app
Version: 0.2.0
Summary: Development flow as Paleofuturistic Python
Author: Paleofuturistic Python
Author-email: Paleofuturistic Python <me@here.now>
Classifier: License :: OSI Approved :: Apache Software License
Classifier: Programming Language :: Python :: 3.12
Requires-Python: >=3.12
